<?xml version = '1.0' encoding = 'UTF-8'?>
<Relation class="oracle.dbtools.crest.model.design.logical.Relation" name="Dijagnoziran" directorySegmentName="seg_0" id="FC467AB8-87FA-1990-3A05-32A72B64320F">
<createdBy>Andrej</createdBy>
<createdTime>2021-01-08 15:20:56 UTC</createdTime>
<ownerDesignName>Servis_racunara</ownerDesignName>
<engineerTo>
<item key="0FF5C3C2-8644-1B59-BE5D-1B79E66C4B4D" value="true"/>
</engineerTo>
<sourcePk>DD3528D5-1D23-2CCD-7900-300E8B417386</sourcePk>
<identifying>false</identifying>
<optionalSource>true</optionalSource>
<optionalTarget>false</optionalTarget>
<sourceCardinality>1</sourceCardinality>
<sourceEntity>AACC6F91-13B1-FAF8-B51F-6D91D43A99D1</sourceEntity>
<targetCardinalityString>*</targetCardinalityString>
<targetEntity>1D4DA5EE-F259-AD05-465E-3E782B8DD2C9</targetEntity>
<transferable>true</transferable>
<deleteRule>NO ACTION</deleteRule>
</Relation>